JuMonC/__init__.py
JuMonC/_version.py
JuMonC/app.py
JuMonC/start.py
JuMonC/authentication/__init__.py
JuMonC/authentication/check.py
JuMonC/authentication/tokens.py
JuMonC/handlers/__init__.py
JuMonC/handlers/auth.py
JuMonC/handlers/base.py
JuMonC/handlers/cache.py
JuMonC/handlers/cpu.py
JuMonC/handlers/gpu.py
JuMonC/handlers/io.py
JuMonC/handlers/job.py
JuMonC/handlers/main.py
JuMonC/handlers/main_memory.py
JuMonC/handlers/network.py
JuMonC/handlers/planed.py
JuMonC/handlers/versionTree.py
JuMonC/helpers/__init__.py
JuMonC/helpers/cmdArguments.py
JuMonC/helpers/convertNumbers.py
JuMonC/helpers/dicthelper.py
JuMonC/helpers/generateToken.py
JuMonC/helpers/startup.py
JuMonC/helpers/PluginManager/__init__.py
JuMonC/helpers/PluginManager/hookspec.py
JuMonC/models/__init__.py
JuMonC/models/dataStore.py
JuMonC/models/planed_tasks.py
JuMonC/models/pluginInformation.py
JuMonC/models/plugins.py
JuMonC/models/cache/__init__.py
JuMonC/models/cache/database.py
JuMonC/models/cache/dbmodel.py
JuMonC/models/cache/helper.py
JuMonC/settings/__init__.py
JuMonC/settings/helpers.py
JuMonC/tasks/CPU.py
JuMonC/tasks/LinuxNetwork.py
JuMonC/tasks/Nvidia.py
JuMonC/tasks/Papi.py
JuMonC/tasks/Plugin.py
JuMonC/tasks/Slurm.py
JuMonC/tasks/__init__.py
JuMonC/tasks/disk.py
JuMonC/tasks/execute_planed_tasks.py
JuMonC/tasks/job.py
JuMonC/tasks/memory.py
JuMonC/tasks/mpi_helper.py
JuMonC/tasks/mpibase.py
JuMonC/tasks/mpihandler.py
JuMonC/tasks/mpiroot.py
JuMonC/tasks/taskID.py
JuMonC/tasks/taskPool.py
JuMonC/tasks/taskSwitcher.py
JuMonC-0.9.1.dist-info/LICENSE
JuMonC-0.9.1.dist-info/METADATA
JuMonC-0.9.1.dist-info/WHEEL
JuMonC-0.9.1.dist-info/entry_points.txt
JuMonC-0.9.1.dist-info/top_level.txt
JuMonC-0.9.1.dist-info/RECORD
