Metadata-Version: 2.1
Name: JuMonC
Version: 0.9.1
Summary: Jülich Monitoring and Control
Home-page: https://gitlab.jsc.fz-juelich.de/coec/jumonc
Author: Christian Witzler
Author-email: c.witzler@fz-juelich.de
License: BSD 3-Clause License
Classifier: License :: OSI Approved :: BSD License
Classifier: Programming Language :: Python :: 3
Classifier: Programming Language :: Python :: 3.9
License-File: LICENSE
Requires-Dist: flask
Requires-Dist: flask-login
Requires-Dist: mpi4py
Requires-Dist: Flask-SQLAlchemy
Requires-Dist: pluggy
Requires-Dist: typing-extensions ; python_version < "3.10"
Provides-Extra: devel
Requires-Dist: python-papi ; extra == 'devel'
Requires-Dist: pynvml ; extra == 'devel'
Requires-Dist: psutil ; extra == 'devel'
Requires-Dist: pyopenssl ; extra == 'devel'
Requires-Dist: prospector ; extra == 'devel'
Requires-Dist: bandit ; extra == 'devel'
Requires-Dist: mypy ; extra == 'devel'
Requires-Dist: pytest ; extra == 'devel'
Requires-Dist: coverage ; extra == 'devel'
Requires-Dist: sqlalchemy[mypy] ; extra == 'devel'
Provides-Extra: full
Requires-Dist: python-papi ; extra == 'full'
Requires-Dist: pynvml ; extra == 'full'
Requires-Dist: psutil ; extra == 'full'
Requires-Dist: pyopenssl ; extra == 'full'
Provides-Extra: gpu
Requires-Dist: pynvml ; extra == 'gpu'
Provides-Extra: nvlm
Requires-Dist: pynvml ; extra == 'nvlm'
Provides-Extra: papi
Requires-Dist: python-papi ; extra == 'papi'
Provides-Extra: ssl
Requires-Dist: pyopenssl ; extra == 'ssl'
Provides-Extra: psutil
Requires-Dist: psutil ; extra == 'psutil'
